{
  "Menus":[
    {
        "Title":"主餐",
        "Foods":[
            {
                "Name":"雞腿飯",
                "Price":90
            },
            {
                "Name":"排骨飯",
                "Price":70
            },
            {
                "Name":"雞排飯",
                "Price":85
            }
        ]

    },
    {
        "Title":"附餐",
        "Foods":[
            {
                "Name":"薯條",
                "Price":40
            },
            {
                "Name":"雞塊",
                "Price":50
            },
            {
                "Name":"薯球",
                "Price":20
            }

        ]

    },
    {
        "Title":"甜點",
          "Foods":[
            {
                "Name":"草莓蛋糕",
                "Price":100
            },
            {
                "Name":"巧克力冰",
                "Price":95
            },
            {
                "Name":"聖代",
                "Price":200
            }

        ]

    }, 
    {
        "Title":"飲料",
        "Foods":[
            {
                "Name":"紅茶",
                "Price":20
            },
            {
                "Name":"綠茶",
                "Price":30
            },
            {
                "Name":"奶茶",
                "Price":40
            },
            {
                "Name":"珍珠奶茶",
                "Price":55
            },
            {
                "Name":"芒果冰沙",
                "Price":110
            },
            {
                "Name":"烏龍奶茶",
                "Price":70
            }

        ]

    }
   

  ] ,
  "Discounts":[
    {
        "Name":"雞排飯買三個打85折",
        "Strategy":"特定品項的打折",
        "Conditions":[
            {
                "Name":"雞排飯",
                "RequirAmount":3,
                "RequirPrice":0
            }
        ],
        "Rewards":[
            {
                "Name":null,
                "RewardType":0,
                "RewardsAmount":0,
                "RewardsPrice":0,
                "RewardsOff":0.85
            }
           
        ]

    },
    {
        "Name":"所有飲料任選三杯打8折",
        "Strategy":"特定品項的打折",
        "Conditions":[
            {
                "Name":"紅茶|綠茶|奶茶|芒果冰沙|珍珠奶茶|烏龍奶茶",
                "RequirAmount":3,
                "RequirPrice":0
            }
            
        ],
        "Rewards":[
            {
                "Name":null,
                "RewardType":0,
                "RewardsAmount":0,
                "RewardsPrice":0,
                "RewardsOff":0.8
            }
           
        ]

    },
    {
        "Name":"雞排飯搭配聖代送紅茶一杯",
        "Strategy":"特定組合送特定品項",
        "Conditions":[
            {
                "Name":"雞排飯",
                "RequirAmount":1,
                "RequirPrice":0

            },
            {
                "Name":"聖代",
                "RequirAmount":1,
                "RequirPrice":0
            }
            
        ],
        "Rewards":[
            {
                "Name":"紅茶",
                "RewardType":0,
                "RewardsAmount":1,
                "RewardsPrice":0,
                "RewardsOff":0
            }
        ]

    },
    {
        "Name":"雞腿飯買兩份外加雞塊兩份就送紅茶兩杯和草莓蛋糕一份",
        "Strategy":"特定組合送特定品項",
        "Conditions":[
            {
                "Name":"雞腿飯",
                "RequirAmount":2,
                "RequirPrice":0
            },
            {
                "Name":"雞塊",
                "RequirAmount":2,
                "RequirPrice":0
            }
            
        ],
        "Rewards":[
            {
                "Name":"紅茶",
                "RewardType":0,
                "RewardsAmount":2,
                "RewardsPrice":0,
                "RewardsOff":0
            },
            {
                "Name":"草莓蛋糕",
                "RewardType":0,
                "RewardsAmount":1,
                "RewardsPrice":0,
                "RewardsOff":0
            }
        ]
    },
    {
        "Name":"排骨飯兩份搭配任選一種配餐就送奶茶",
        "Strategy":"特定組合送特定品項",
        "Conditions":[
            {
                "Name":"排骨飯",
                "RequirAmount":2,
                "RequirPrice":0
            },
            {
                "Name":"雞塊|薯條|薯球",
                "RequirAmount":1,
                "RequirPrice":0
            }
            
        ],
        "Rewards":[
            {
                "Name":"奶茶",
                "RewardType":0,
                "RewardsAmount":1,
                "RewardsPrice":0,
                "RewardsOff":0
            }
        ]
    },
    {
        "Name":"所有飲料買三杯就送一杯(送最便宜品項)",
        "Strategy":"特定組合送特定品項",
        "Conditions":[
            {
                "Name":"紅茶|綠茶|奶茶|芒果冰沙|珍珠奶茶|烏龍奶茶",
                "RequirAmount":3,
                "RequirPrice":0
            }
        ],
        "Rewards":[
            {
                "Name":"紅茶|綠茶|奶茶|芒果冰沙|珍珠奶茶|烏龍奶茶",
                "RewardType":"Min",
                "RewardsAmount":1,
                "RewardsPrice":0,
                "RewardsOff":0
            }
        ]
    },
    {
        "Name":"指定奶茶系列任選兩杯送一杯送最貴價格",
        "Strategy":"特定組合送特定品項",
        "Conditions":[
            {
                "Name":"奶茶|珍珠奶茶|烏龍奶茶",
                "RequirAmount":2,
                "RequirPrice":0
            }
        ],
        "Rewards":[
            {
                "Name":"奶茶|珍珠奶茶|烏龍奶茶",
                "RewardType":"Max",
                "RewardsAmount":1,
                "RewardsPrice":0,
                "RewardsOff":0
            }
        ]
    },
    {
        "Name":"所有飲料任選三杯送一杯有購買的隨機飲料",
        "Strategy":"特定組合送特定品項",
        "Conditions":[
            {
                "Name":"紅茶|綠茶|奶茶|芒果冰沙|珍珠奶茶|烏龍奶茶",
                "RequirAmount":3,
                "RequirPrice":0
            }
        ],
        "Rewards":[
            {
                "Name":"紅茶|綠茶|奶茶|芒果冰沙|珍珠奶茶|烏龍奶茶",
                "RewardType":"Random",
                "RewardsAmount":1,
                "RewardsPrice":0,
                "RewardsOff":0
            }
        ]
    },
    {
        "Name":"雞腿飯買二送一",
        "Strategy":"特定組合送特定品項",
        "Conditions":[
            {
                "Name":"雞腿飯",
                "RequirAmount":2,
                "RequirPrice":0
            }
        ],
        "Rewards":[
            {
                "Name":"雞腿飯",
                "RewardType":0,
                "RewardsAmount":1,
                "RewardsPrice":0,
                "RewardsOff":0
            }
        ]
    },
    {
        "Name":"全場消費滿500折100",
        "Strategy":"消費總額的打折",
        "Conditions":[
            {
                "Name":null,
                "RequirAmount":0,
                "RequirPrice":500

            }
        ],
        "Rewards":[
            {
                "Name":null,
                "RewardType":0,
                "RewardsAmount":0,
                "RewardsPrice":-100,
                "RewardsOff":0
            }

        ]
    },
    {
        "Name":"全場一律打9折",
        "Strategy":"消費總額的打折",
        "Conditions":[],
        "Rewards":[
            {
                "Name":null,
                "RewardType":0,
                "RewardsAmount":0,
                "RewardsPrice":0,
                "RewardsOff":0.9
            }

        ]
    },
    {
        "Name":"排骨飯搭配薯條100元",
        "Strategy":"特定組合的優惠價",
        "Conditions":[
            {  
                "Name":"排骨飯",
                "RequirAmount":1,
                "RequirPrice":0
            },
            {
                "Name":"薯條",
                "RequirAmount":1,
                "RequirPrice":0
            }
        ],
        "Rewards":[
            {
                "Name":null,
                "RewardType":0,
                "RewardsAmount":0,
                "RewardsPrice":100,
                "RewardsOff":0
            }

        ]
    },
    {
        "Name":"雞排飯買兩份外加薯條兩份180元",
        "Strategy":"特定組合的優惠價",
        "Conditions":[
            {  
                "Name":"雞排飯",
                "RequirAmount":2,
                "RequirPrice":0
            },
            {
                "Name":"薯條",
                "RequirAmount":2,
                "RequirPrice":0
            }
        ],
        "Rewards":[
            {
                "Name":null,
                "RewardType":0,
                "RewardsAmount":0,
                "RewardsPrice":180,
                "RewardsOff":0
            }
        ]
    },
    {
        "Name":"雞排飯3份搭配薯條1份打65折",
        "Strategy":"特定組合的優惠價",
        "Conditions":[
            {  
                "Name":"雞排飯",
                "RequirAmount":3,
                "RequirPrice":0
            },
            {
                "Name":"薯條",
                "RequirAmount":1,
                "RequirPrice":0
            }
        ],
        "Rewards":[
            {
                "Name":null,
                "RewardType":0,
                "RewardsAmount":0,
                "RewardsPrice":0,
                "RewardsOff":0.65
            }
        ]
    },
    {
        "Name":"飲料均一價20元",
        "Strategy":"特定組合的優惠價",
        "Conditions":[
            {  
                "Name":"紅茶|綠茶|奶茶|芒果冰沙|珍珠奶茶|烏龍奶茶",
                "RequirAmount":1,
                "RequirPrice":0
            }
        ],
        "Rewards":[
            {
                "Name":null,
                "RewardType":0,
                "RewardsAmount":0,
                "RewardsPrice":20,
                "RewardsOff":0
            }
        ]
    }
  ]  
}